pyretroterm/__init__.py
pyretroterm/config.py
pyretroterm/nbtosession.py
pyretroterm/pyretroterm.py
pyretroterm/themes2.py
pyretroterm/themes3.py
pyretroterm/helpers/__init__.py
pyretroterm/helpers/auth_helper.py
pyretroterm/helpers/credslib.py
pyretroterm/helpers/settings.py
pyretroterm/helpers/utils.py
pyretroterm/routers/__init__.py
pyretroterm/routers/auth.py
pyretroterm/routers/search.py
pyretroterm/routers/workspace.py
pyretroterm/ssh/__init__.py
pyretroterm/ssh/connection_checker.py
pyretroterm/ssh/pysshpass.py
pyretroterm/ssh/ssh_manager.py
pyretroterm/ssh/sshschemahandler.py
pyretroterm/ssh/sshshell.py
pyretroterm/ssh/sshshellreader.py
pyretroterm/static/doom.html
pyretroterm/static/doom.wasm
pyretroterm/static/doom.wasm.sav
pyretroterm/static/main.js
pyretroterm/static/python.webp
pyretroterm/static/qtsshcon.html
pyretroterm/static/qtsshcon_light.html
pyretroterm/static/sshconfrontend.js
pyretroterm/static/xterm-addon-fit.min.js
pyretroterm/static/xterm.min.css
pyretroterm/static/xterm.min.js
pyretroterm/static/css/amber
pyretroterm/static/css/dark.css
pyretroterm/static/css/default-save.css
pyretroterm/static/css/retro_green
pyretroterm/static/css/theme-blue.css
pyretroterm/static/css/theme-crt-amber.css
pyretroterm/static/css/theme-crt-green.css
pyretroterm/static/css/theme-crt-mono.css
pyretroterm/static/css/theme-default-green.css
pyretroterm/static/css/theme-default.css
pyretroterm/static/css/theme-forest-green.css
pyretroterm/static/css/theme-forest-light.css
pyretroterm/static/css/theme-green.css
pyretroterm/static/css/theme-light.css
pyretroterm/static/css/theme-paper-white.css
pyretroterm/static/css/theme-paper.css
pyretroterm/static/css/velociterm.css
pyretroterm/static/css/xterm.css
pyretroterm/static/images/python.png
pyretroterm/static/images/python1.png
pyretroterm/static/images/python2.png
pyretroterm/static/js/custom.js
pyretroterm/static/js/velociterm.js
pyretroterm/static/js/xterm-addon-fit.js
pyretroterm/static/js/xterm.js
pyRetroTerm-0.2.1.dist-info/METADATA
pyRetroTerm-0.2.1.dist-info/WHEEL
pyRetroTerm-0.2.1.dist-info/entry_points.txt
pyRetroTerm-0.2.1.dist-info/top_level.txt
pyRetroTerm-0.2.1.dist-info/RECORD
